Metadata-Version: 2.1
Name: simple-mock
Version: 0.0.1
Summary: simple patching for python functions
Home-page: https://github.com/satyavls/simple_mock
Author: satyavijay shelke
Author-email: satyavls99@gmail.com
License: UNKNOWN
Platform: UNKNOWN
Classifier: License :: OSI Approved :: MIT License
Classifier: Programming Language :: Python :: 2.7
